{
  "meta": {
    "file": "w35_i003_Tuan_35_-_On_tap_cuoi_nam_hoc_Tiet_3.pptx",
    "subject": "tieng-viet",
    "path": "docs\\research\\official-sources\\downloads\\hoc10\\lop4\\tieng-viet\\slides\\w35_i003_Tuan_35_-_On_tap_cuoi_nam_hoc_Tiet_3.pptx",
    "slideCount": 19
  },
  "slides": [
    {
      "slideNo": 1,
      "type": "cover",
      "paragraphs": [
        "Tuần 35",
        "Ôn tập cuối năm học",
        "(Tiết 3)",
        "TIẾNG VIỆT 4",
        "Tập 2"
      ]
    },
    {
      "slideNo": 2,
      "type": "empty",
      "paragraphs": []
    },
    {
      "slideNo": 3,
      "type": "questions",
      "paragraphs": [
        "Đố em: Bàn gì mà lại bước gần bước xa?",
        "(Đáp án: Bàn chân)"
      ]
    },
    {
      "slideNo": 4,
      "type": "empty",
      "paragraphs": []
    },
    {
      "slideNo": 5,
      "type": "content",
      "paragraphs": [
        "Đánh giá kĩ năng",
        "đọc thành tiếng,",
        "học thuộc lòng"
      ]
    },
    {
      "slideNo": 6,
      "type": "questions",
      "paragraphs": [
        "Em hãy đọc thuộc lòng các khổ thơ hoặc bài thơ sau:",
        "Chẳng phải chuyện đùa",
        "Chuyện cổ tích về loài người",
        "Em bé Bảo Ninh"
      ]
    },
    {
      "slideNo": 7,
      "type": "content",
      "paragraphs": [
        "Kể chuyện"
      ]
    },
    {
      "slideNo": 8,
      "type": "questions",
      "paragraphs": [
        "Quan sát gợi ý và kể lại câu chuyện Hơn cả phép mầu",
        "Ông Ha-ri-xơ phát hiện ra điều gì trong chiếc lon đựng xu lẻ của mình?",
        "Vì sao ông không bán vật quý đó mà ngồi chờ người mất của quay lại nhận?",
        "Vợ chồng cô Đa-linh đã đền đáp người ăn xin thật thà, nhân hậu bằng cách nào?",
        "Tại trường quay của hãng truyền hình, ông Ha-ri-xơ đã gặp ai và ông nói gì?",
        "Gợi ý"
      ]
    },
    {
      "slideNo": 9,
      "type": "content",
      "paragraphs": [
        "Ông Ha-ri-xơ là một người vô gia cư ở thành phố Kan-dát-xơ thuộc bang Mít-xu-ri (nước Mỹ). Một lần, ông vô tình phát hiện một chiếc nhẫn kim cương đắt giá nằm lẫn lộn trong lon chứa đồng xu lẻ mà người đi đường thường thả vào đẩy cho ông. Nhìn thoáng qua, ông đoán được đây là chiếc nhẫn cưới của một phụ nữ bị rớt vào khi dừng lại cho ông vài đồng xu."
      ]
    },
    {
      "slideNo": 10,
      "type": "content",
      "paragraphs": [
        "Như bao người ăn xin khác, khi có được món đồ giá trị thì suy nghĩ đầu tiên là đem đi bán và ông Ha-ri-xơ cũng làm như vậy. Ông đến cửa hàng trang sức để đổi chiếc nhẫn lấy tiền. Khi được nhân viên cửa hàng báo giá 4 000 đô la cho chiếc nhẫn kim cương, ông sực tỉnh với suy nghĩ: người mất chiếc nhẫn hẳn sẽ đau lòng khi không tìm thấy kỉ vật quý giá của mình. Thế là ông quyết định không bán mà ngồi chờ người phụ nữ ấy quay lại."
      ]
    },
    {
      "slideNo": 11,
      "type": "content",
      "paragraphs": [
        "Cảm kích trước tấm lòng nhân ái của ông, cô Đa-linh và chồng quyết định lập quỹ trên một trang mạng với mục đích kêu gọi người dân đóng góp tiền để giúp ông Ha-ri-xơ có một chỗ ở. Chỉ trong thời gian ngắn, số tiền đóng góp đã lên tới 185 000 đô la."
      ]
    },
    {
      "slideNo": 12,
      "type": "content",
      "paragraphs": [
        "Câu chuyện “cổ tích” với một kết thúc có hậu giữa ông già ăn xin và người phụ nữ nhanh chóng lan rộng trên mạng. Không ngờ thông tin ấy lại là chìa khoá để em gái ông tìm lại được người anh trai thất lạc 16 năm mà bà nghĩ đã chết từ lâu.",
        "Ông Ha-ri-xơ nghẹn ngào chia sẻ khi gặp lại người thân tại trường quay của Hãng truyền hình NBC (Mỹ): “Đây là phần thưởng quý giá nhất mà tôi nhận được.”. Ông đã khóc trong niềm vui đón nhận món quả quá đỗi bất ngờ này vì ông không ngờ rằng “ông đã được đền đáp xứng đáng hơn ông nghĩ”."
      ]
    },
    {
      "slideNo": 13,
      "type": "questions",
      "paragraphs": [
        "Trao đổi về câu chuyện Hơn cả phép mầu",
        "Vì sao câu chuyện được đặt tên là \"Hơn cả phép mầu”?",
        "Chọn một tên khác cho câu chuyện."
      ]
    },
    {
      "slideNo": 14,
      "type": "content",
      "paragraphs": [
        "Chuyện được đặt tên là “Hơn cả phép mầu” vì những điều tốt đẹp đến với ông Ha-ri-xơ quá kì diệu, ngoài sức tưởng tượng của con người.",
        "Gợi ý",
        "Trao đổi về câu chuyện Hơn cả phép mầu"
      ]
    },
    {
      "slideNo": 15,
      "type": "content",
      "paragraphs": [
        "b. HS có thể chọn cả ba tên như SGK gợi ý.",
        "Gợi ý",
        "Trao đổi về câu chuyện Hơn cả phép mầu"
      ]
    },
    {
      "slideNo": 16,
      "type": "empty",
      "paragraphs": []
    },
    {
      "slideNo": 17,
      "type": "content",
      "paragraphs": [
        "Ôn lại kiến thức đã học",
        "Chuẩn bị nội dung tiết sau:",
        "Ôn tập cuối học kì II (Tiết 4)"
      ]
    },
    {
      "slideNo": 18,
      "type": "empty",
      "paragraphs": []
    },
    {
      "slideNo": 19,
      "type": "content",
      "paragraphs": [
        "Để kết nối cộng đồng giáo viên và nhận thêm nhiều tài liệu giảng dạy,",
        "mời quý thầy cô tham gia Group Facebook",
        "theo đường link:",
        "Hoc10 – Đồng hành cùng giáo viên tiểu học",
        "Hoặc truy cập qua QR code"
      ]
    }
  ],
  "extracted": {
    "title": "Tuần 35 Ôn tập cuối năm học (Tiết 3)",
    "questions": [
      {
        "type": "question",
        "text": "Đố em: Bàn gì mà lại bước gần bước xa?",
        "slide": 3
      },
      {
        "type": "task",
        "text": "Em hãy đọc thuộc lòng các khổ thơ hoặc bài thơ sau:",
        "slide": 6
      },
      {
        "type": "question",
        "text": "Ông Ha-ri-xơ phát hiện ra điều gì trong chiếc lon đựng xu lẻ của mình?",
        "slide": 8
      },
      {
        "type": "question",
        "text": "Vì sao ông không bán vật quý đó mà ngồi chờ người mất của quay lại nhận?",
        "slide": 8
      },
      {
        "type": "question",
        "text": "Vợ chồng cô Đa-linh đã đền đáp người ăn xin thật thà, nhân hậu bằng cách nào?",
        "slide": 8
      },
      {
        "type": "question",
        "text": "Tại trường quay của hãng truyền hình, ông Ha-ri-xơ đã gặp ai và ông nói gì?",
        "slide": 8
      },
      {
        "type": "question",
        "text": "Vì sao câu chuyện được đặt tên là \"Hơn cả phép mầu”?",
        "slide": 13
      },
      {
        "type": "task",
        "text": "Chọn một tên khác cho câu chuyện.",
        "slide": 13
      }
    ],
    "vocab": [],
    "keyPoints": []
  }
}