{
  "meta": {
    "file": "w26_i000_Tuan_26.pptx",
    "subject": "hoat-dong-trai-nghiem",
    "path": "docs\\research\\official-sources\\downloads\\hoc10\\lop4\\hoat-dong-trai-nghiem\\slides\\w26_i000_Tuan_26.pptx",
    "slideCount": 23
  },
  "slides": [
    {
      "slideNo": 1,
      "type": "content",
      "paragraphs": [
        "HĐTN 4",
        "HĐTN 4",
        "Chủ đề 7:",
        "Gắn kết yêu thương",
        "Tuần 26"
      ]
    },
    {
      "slideNo": 2,
      "type": "empty",
      "paragraphs": []
    },
    {
      "slideNo": 3,
      "type": "content",
      "paragraphs": [
        "Tham gia hội diễn văn nghệ chào mừng ngày Quốc tế Phụ nữ 8-3.",
        "Lắng nghe và chia sẻ những câu chuyện về sự gắn kết yêu thương trong gia đình.",
        "Chào mừng ngày Quốc tế Phụ nữ 8-3"
      ]
    },
    {
      "slideNo": 4,
      "type": "content",
      "paragraphs": [
        "Các em lắng nghe và xem video về bài hát “Cha và con gái”, sau đó nêu cảm nhận của bản thân khi nghe bài hát",
        "KHỞI ĐỘNG"
      ]
    },
    {
      "slideNo": 5,
      "type": "empty",
      "paragraphs": []
    },
    {
      "slideNo": 6,
      "type": "activity",
      "paragraphs": [
        "Hoạt động 3: Làm Hộp rối kể chuyện",
        "Các em thực hành làm Hộp rối kể chuyện theo các bước hướng dẫn sau:",
        "Tô màu hình chân dung các thành viên trong gia đình",
        "Dùng kéo cắt rời hình các thành viên trong gia đình",
        "Vẽ chân dung các thành viên trong gia đình lên giấy, nên sử dụng giấy bìa cứng để hình chân dung sau khi cắt được đẹp hơn"
      ]
    },
    {
      "slideNo": 7,
      "type": "activity",
      "paragraphs": [
        "Hoạt động 3: Làm Hộp rối kể chuyện",
        "Các em thực hành làm Hộp rối kể chuyện theo các bước hướng dẫn sau:",
        "Làm khung hộp rối từ hộp các-tông đã chuẩn bị",
        "Sắp xếp các nhân vật vào hộp rối theo ý tưởng của mình",
        "Dán hình từng thành viên trong gia đình lên que tre"
      ]
    },
    {
      "slideNo": 8,
      "type": "theory",
      "paragraphs": [
        "Sự tích cực, khéo léo của các em đã sáng tạo nên các nhân vật tượng trưng cho các thành viên trong gia đình để đưa vào Hộp rối kể chuyện.",
        "Kết luận"
      ]
    },
    {
      "slideNo": 9,
      "type": "activity",
      "paragraphs": [
        "Hoạt động 4: Kể câu chuyện về gia đình",
        "HOẠT ĐỘNG NHÓM",
        "Các nhóm hãy sử dụng hộp rối đã làm ở Hoạt động 3 để kể câu chuyện về sự gắn kết yêu thương giữa các thành viên trong gia đình theo các bước hướng dẫn cho sẵn dưới đây."
      ]
    },
    {
      "slideNo": 10,
      "type": "content",
      "paragraphs": [
        "Các thành viên trong nhóm cùng trao đổi để xây dựng cốt truyện, viết kịch bản ra giấy.",
        "Chuẩn bị lời thoại để thể hiện.",
        "CÁC BƯỚC HƯỚNG DẪN"
      ]
    },
    {
      "slideNo": 11,
      "type": "content",
      "paragraphs": [
        "Phân chia thể hiện các nhân vật trong câu chuyện.",
        "Sắp xếp hình chân dung các thành viên trong gia đình đã làm ở Hoạt động 3 vào hộp rối cho phù hợp với cốt truyện đã xây dựng.",
        "CÁC BƯỚC HƯỚNG DẪN"
      ]
    },
    {
      "slideNo": 12,
      "type": "content",
      "paragraphs": [
        "Sau khi hoàn thành phần thảo luận và chuẩn bị, các nhóm hãy viết kịch bản và tập luyện kể câu chuyện với nhau bằng hộp rối của nhóm mình."
      ]
    },
    {
      "slideNo": 13,
      "type": "content",
      "paragraphs": [
        "CHIA SẺ",
        "Sau khi kết thúc tập luyện, lần lượt các nhóm kể câu chuyện bằng hộp rối nhóm mình ở trước lớp và các bạn khác sẽ chia sẻ cảm nhận về các câu chuyện được nghe."
      ]
    },
    {
      "slideNo": 14,
      "type": "theory",
      "paragraphs": [
        "KẾT LUẬN",
        "Mỗi câu chuyện của các em đều chứa đựng những kỉ niệm, tình cảm yêu thương mà các em dành cho gia đình mình.",
        "Các em hãy tích cực thực hiện những việc làm cụ thể, phù hợp với lứa tuổi để gắn kết yêu thương giữa các thành viên trong gia đình."
      ]
    },
    {
      "slideNo": 15,
      "type": "reflection",
      "paragraphs": [
        "Các em xem đoạn video sau và trả lời câu hỏi dưới đây:",
        "Em rút ra được bài học gì từ video trên?"
      ]
    },
    {
      "slideNo": 16,
      "type": "content",
      "paragraphs": [
        "Bài học rút ra:",
        "Gia đình là nơi vun đắp tình yêu thương, xây dựng tinh thần trách nhiệm đồng thời cũng là nơi lưu truyền giá trị đạo đức từ thế hệ này sang thế hệ khác."
      ]
    },
    {
      "slideNo": 17,
      "type": "empty",
      "paragraphs": []
    },
    {
      "slideNo": 18,
      "type": "content",
      "paragraphs": [
        "Báo cáo kết quả thực hiện kế hoạch Gắn kết yêu thương",
        "• Nêu những việc em đã làm tạo sự gắn kết yêu thương giữa các thành viên trong gia đình.",
        "• Chia sẻ cảm xúc khi thực hiện những việc làm để gắn kết các thành viên trong gia đình em."
      ]
    },
    {
      "slideNo": 19,
      "type": "empty",
      "paragraphs": []
    },
    {
      "slideNo": 20,
      "type": "content",
      "paragraphs": [
        "Chia sẻ với người thân về những việc làm để gắn kết yêu thương giữa các thành viên trong gia đình của các bạn trong lớp."
      ]
    },
    {
      "slideNo": 21,
      "type": "content",
      "paragraphs": [
        "HƯỚNG DẪN VỀ NHÀ",
        "Đọc và chuẩn bị bài học Tuần 27."
      ]
    },
    {
      "slideNo": 22,
      "type": "empty",
      "paragraphs": []
    },
    {
      "slideNo": 23,
      "type": "content",
      "paragraphs": [
        "Để kết nối cộng đồng giáo viên và nhận thêm nhiều tài liệu giảng dạy,",
        "mời quý thầy cô tham gia Group Facebook",
        "theo đường link:",
        "Hoc10 – Đồng hành cùng giáo viên tiểu học",
        "Hoặc truy cập qua QR code"
      ]
    }
  ],
  "extracted": {
    "title": "w26 i000 Tuan 26",
    "questions": [
      {
        "type": "task",
        "text": "Vẽ chân dung các thành viên trong gia đình lên giấy, nên sử dụng giấy bìa cứng để hình chân dung sau khi cắt được đẹp hơn",
        "slide": 6
      },
      {
        "type": "question",
        "text": "Em rút ra được bài học gì từ video trên?",
        "slide": 15
      },
      {
        "type": "task",
        "text": "Đọc và chuẩn bị bài học Tuần 27.",
        "slide": 21
      }
    ],
    "vocab": [],
    "keyPoints": [
      "Sự tích cực, khéo léo của các em đã sáng tạo nên các nhân vật tượng trưng cho các thành viên trong gia đình để đưa vào Hộp rối kể chuyện.",
      "Mỗi câu chuyện của các em đều chứa đựng những kỉ niệm, tình cảm yêu thương mà các em dành cho gia đình mình.",
      "Các em hãy tích cực thực hiện những việc làm cụ thể, phù hợp với lứa tuổi để gắn kết yêu thương giữa các thành viên trong gia đình.",
      "Các em xem đoạn video sau và trả lời câu hỏi dưới đây:",
      "Em rút ra được bài học gì từ video trên?"
    ]
  }
}