{
  "meta": {
    "file": "w07_i002_Tuan_7_-_Bai_21_Hai_duong_thang_vuong_goc._Ve_hai_duong_thang_vuong_goc_-_Tiet_2.pptx",
    "subject": "toan",
    "path": "docs\\research\\official-sources\\downloads\\hoc10\\lop4\\toan\\slides\\w07_i002_Tuan_7_-_Bai_21_Hai_duong_thang_vuong_goc._Ve_hai_duong_thang_vuong_goc_-_Tiet_2.pptx",
    "slideCount": 23
  },
  "slides": [
    {
      "slideNo": 1,
      "type": "cover",
      "paragraphs": [
        "TOÁN 4",
        "Tập 1",
        "Tuần 7",
        "Bài 21: Hai đường thẳng vuông góc. Vẽ hai đường thẳng vuông góc - Tiết 2"
      ]
    },
    {
      "slideNo": 2,
      "type": "content",
      "paragraphs": [
        "Ấn để đến trang sách"
      ]
    },
    {
      "slideNo": 3,
      "type": "content",
      "paragraphs": [
        "Ong",
        "non",
        "việc",
        "học"
      ]
    },
    {
      "slideNo": 4,
      "type": "questions",
      "paragraphs": [
        "Câu 1: Góc vuông có số đo bằng",
        "A. 90°.",
        "B. 30°.",
        "C. 180°.",
        "D. 100°."
      ]
    },
    {
      "slideNo": 5,
      "type": "questions",
      "paragraphs": [
        "Câu 2: Hai đường thằng vuông góc với nhau tạo thành",
        "A. 1 góc vuông.",
        "B. 2 góc vuông.",
        "C. 3 góc vuông.",
        "D. 4 góc vuông."
      ]
    },
    {
      "slideNo": 6,
      "type": "content",
      "paragraphs": [
        "Ấn để đến trang sách"
      ]
    },
    {
      "slideNo": 7,
      "type": "content",
      "paragraphs": [
        "Vẽ hai đường thẳng vuông góc",
        "Vẽ đường thẳng CD đi qua điểm E (điểm E không nằm trên đường thẳng AB) và vuông góc với đường thẳng AB."
      ]
    },
    {
      "slideNo": 8,
      "type": "content",
      "paragraphs": [
        "Bước 1: Đặt ê ke sao cho một cạnh của ê ke nằm trên đường thẳng AB.",
        "Bước 2: Dịch chuyển ê ke trên đường thẳng AB đến vị trí điểm E."
      ]
    },
    {
      "slideNo": 9,
      "type": "content",
      "paragraphs": [
        "Bước 3: Chọn điểm C trên cạnh còn lại của ê ke."
      ]
    },
    {
      "slideNo": 10,
      "type": "content",
      "paragraphs": [
        "Bước 4: Dùng thước thẳng kẻ đường thẳng CE. Ta được đường thẳng CD đi qua điểm E và vuông góc với đường thẳng AB."
      ]
    },
    {
      "slideNo": 11,
      "type": "theory",
      "paragraphs": [
        "Chú ý: Khi E nằm trên đường thẳng AB, cách vẽ vẫn được thực hiện các bước tương tự.",
        "Giống nhau"
      ]
    },
    {
      "slideNo": 12,
      "type": "content",
      "paragraphs": [
        "Ấn để đến trang sách"
      ]
    },
    {
      "slideNo": 13,
      "type": "activity",
      "paragraphs": [
        "Bài tập 5 (SGK – tr52):",
        "Vẽ đường thẳng PQ đi qua điểm X và vuông góc với đường",
        "thẳng MN trong các trường hợp sau đây:",
        "a)                                                          b)"
      ]
    },
    {
      "slideNo": 14,
      "type": "activity",
      "paragraphs": [
        "Bài tập 5 (SGK – tr52):",
        "Vẽ đường thẳng PQ đi qua điểm X và vuông góc với đường",
        "thẳng MN trong các trường hợp sau đây:",
        "c)                                                         d)"
      ]
    },
    {
      "slideNo": 15,
      "type": "activity",
      "paragraphs": [
        "Bài tập 6 (SGK – tr53):",
        "Vẽ hình theo mẫu sau:"
      ]
    },
    {
      "slideNo": 16,
      "type": "content",
      "paragraphs": [
        "Ấn để đến trang sách"
      ]
    },
    {
      "slideNo": 17,
      "type": "activity",
      "paragraphs": [
        "Bài tập 7 (SGK – tr53):",
        "Kể một tình huống có vận dụng đường vuông góc trong cuộc sống mà em biết",
        "Ví dụ: Để đo thành tích bật xa, người ta đo độ dài đường vuông",
        "góc từ điểm tiếp đất gần nhất của cơ thể đến vạch xuất phát."
      ]
    },
    {
      "slideNo": 18,
      "type": "activity",
      "paragraphs": [
        "Bài tập 7 (SGK – tr53)",
        "Ví dụ: Dây phơi quần áo vuông góc với hai trụ"
      ]
    },
    {
      "slideNo": 19,
      "type": "questions",
      "paragraphs": [
        "CỦNG CỐ, DẶN DÒ",
        "Qua bài học hôm nay, em biết thêm được điều gì?"
      ]
    },
    {
      "slideNo": 20,
      "type": "content",
      "paragraphs": [
        "Ấn để đến trang sách"
      ]
    },
    {
      "slideNo": 21,
      "type": "activity",
      "paragraphs": [
        "Ôn tập kiến thức đã học",
        "Hoàn thành bài tập trong VBT",
        "Đọc và chuẩn bị trước Bài 22:",
        "Hai đường thẳng song song.",
        "Vẽ hai đường thẳng song song"
      ]
    },
    {
      "slideNo": 22,
      "type": "empty",
      "paragraphs": []
    },
    {
      "slideNo": 23,
      "type": "content",
      "paragraphs": [
        "Để kết nối cộng đồng giáo viên và nhận thêm nhiều tài liệu giảng dạy,",
        "mời quý thầy cô tham gia Group Facebook",
        "theo đường link:",
        "Hoc10 – Đồng hành cùng giáo viên tiểu học",
        "Hoặc truy cập qua QR code"
      ]
    }
  ],
  "extracted": {
    "title": "TOÁN 4 Tập 1 Tuần 7",
    "questions": [
      {
        "type": "task",
        "text": "Vẽ hai đường thẳng vuông góc",
        "slide": 7
      },
      {
        "type": "task",
        "text": "Vẽ đường thẳng CD đi qua điểm E (điểm E không nằm trên đường thẳng AB) và vuông góc với đường thẳng AB.",
        "slide": 7
      },
      {
        "type": "task",
        "text": "Vẽ đường thẳng PQ đi qua điểm X và vuông góc với đường",
        "slide": 13
      },
      {
        "type": "task",
        "text": "Vẽ đường thẳng PQ đi qua điểm X và vuông góc với đường",
        "slide": 14
      },
      {
        "type": "task",
        "text": "Vẽ hình theo mẫu sau:",
        "slide": 15
      },
      {
        "type": "task",
        "text": "Kể một tình huống có vận dụng đường vuông góc trong cuộc sống mà em biết",
        "slide": 17
      },
      {
        "type": "question",
        "text": "Qua bài học hôm nay, em biết thêm được điều gì?",
        "slide": 19
      },
      {
        "type": "task",
        "text": "Đọc và chuẩn bị trước Bài 22:",
        "slide": 21
      },
      {
        "type": "task",
        "text": "Vẽ hai đường thẳng song song",
        "slide": 21
      }
    ],
    "vocab": [],
    "keyPoints": [
      "Chú ý: Khi E nằm trên đường thẳng AB, cách vẽ vẫn được thực hiện các bước tương tự."
    ]
  }
}