{
  "meta": {
    "file": "w26_i001_Tuan_26_-_Bai_73_Cong_cac_phan_so_cung_mau_so_-_Tiet_1.pptx",
    "subject": "toan",
    "path": "docs\\research\\official-sources\\downloads\\hoc10\\lop4\\toan\\slides\\w26_i001_Tuan_26_-_Bai_73_Cong_cac_phan_so_cung_mau_so_-_Tiet_1.pptx",
    "slideCount": 16
  },
  "slides": [
    {
      "slideNo": 1,
      "type": "cover",
      "paragraphs": [
        "TOÁN 4",
        "Tập 2",
        "Tuần 26",
        "Bài 73: Cộng các phân số cùng mẫu số - Tiết 1"
      ]
    },
    {
      "slideNo": 2,
      "type": "content",
      "paragraphs": [
        "Ấn để đến trang sách"
      ]
    },
    {
      "slideNo": 3,
      "type": "empty",
      "paragraphs": []
    },
    {
      "slideNo": 4,
      "type": "content",
      "paragraphs": [
        "Ấn để đến trang sách"
      ]
    },
    {
      "slideNo": 5,
      "type": "questions",
      "paragraphs": [
        "1. Tính",
        "= ?",
        "Lấy ra một băng giấy, tô màu \t     băng giấy, sau đó tô màu tiếp       băng giấy.",
        "5 + 2",
        "Vậy"
      ]
    },
    {
      "slideNo": 6,
      "type": "content",
      "paragraphs": [
        "2. Nhận xét",
        "1 + 5",
        "Ví dụ:",
        "Muốn cộng hai phân số có cùng mẫu số, ta cộng hai tử số với nhau và giữ nguyên mẫu số."
      ]
    },
    {
      "slideNo": 7,
      "type": "content",
      "paragraphs": [
        "Ấn để đến trang sách"
      ]
    },
    {
      "slideNo": 8,
      "type": "activity",
      "paragraphs": [
        "Bài tập 1 (SGK – tr49)",
        "Tính:",
        "2 + 1",
        "6 + 2"
      ]
    },
    {
      "slideNo": 9,
      "type": "activity",
      "paragraphs": [
        "Bài tập 1 (SGK – tr49)",
        "Tính:",
        "2 + 5",
        "12",
        "18",
        "18",
        "12 + 7",
        "18",
        "19",
        "18"
      ]
    },
    {
      "slideNo": 10,
      "type": "activity",
      "paragraphs": [
        "Bài tập 1 (SGK – tr49)",
        "Tính:",
        "3 + 4",
        "7 + 2"
      ]
    },
    {
      "slideNo": 11,
      "type": "activity",
      "paragraphs": [
        "Bài tập 3 (SGK – tr49)",
        "Chọn cách tính đúng:",
        "HOẠT ĐỘNG CẶP ĐÔI",
        "4 + 3",
        "5 + 5",
        "10",
        "A.",
        "4 + 3",
        "B."
      ]
    },
    {
      "slideNo": 12,
      "type": "questions",
      "paragraphs": [
        "CỦNG CỐ, DẶN DÒ",
        "Qua bài học hôm nay em học được những gì?",
        "Muốn cộng hai phân số cùng mẫu số ta làm thế nào?"
      ]
    },
    {
      "slideNo": 13,
      "type": "content",
      "paragraphs": [
        "Ấn để đến trang sách"
      ]
    },
    {
      "slideNo": 14,
      "type": "activity",
      "paragraphs": [
        "Ôn tập",
        "kiến thức đã học",
        "Hoàn thành",
        "bài tập trong VBT",
        "Đọc và chuẩn",
        "bị trước Bài 73: Cộng các phân số cùng mẫu số - Tiết 2"
      ]
    },
    {
      "slideNo": 15,
      "type": "empty",
      "paragraphs": []
    },
    {
      "slideNo": 16,
      "type": "content",
      "paragraphs": [
        "Để kết nối cộng đồng giáo viên và nhận thêm nhiều tài liệu giảng dạy,",
        "mời quý thầy cô tham gia Group Facebook",
        "theo đường link:",
        "Hoc10 – Đồng hành cùng giáo viên tiểu học",
        "Hoặc truy cập qua QR code"
      ]
    }
  ],
  "extracted": {
    "title": "TOÁN 4 Tập 2 Tuần 26",
    "questions": [
      {
        "type": "task",
        "text": "Chọn cách tính đúng:",
        "slide": 11
      },
      {
        "type": "question",
        "text": "Qua bài học hôm nay em học được những gì?",
        "slide": 12
      },
      {
        "type": "question",
        "text": "Muốn cộng hai phân số cùng mẫu số ta làm thế nào?",
        "slide": 12
      },
      {
        "type": "task",
        "text": "Đọc và chuẩn",
        "slide": 14
      }
    ],
    "vocab": [],
    "keyPoints": []
  }
}